spotify_cover_maker/__init__.py
spotify_cover_maker/__main__.py
spotify_cover_maker/cli/__init__.py
spotify_cover_maker/cli/app.py
spotify_cover_maker/cli/ui/__init__.py
spotify_cover_maker/cli/ui/editor.py
spotify_cover_maker/cli/ui/editors/__init__.py
spotify_cover_maker/cli/ui/editors/gradient.py
spotify_cover_maker/cli/ui/root.py
spotify_cover_maker/cli/ui/screens/__init__.py
spotify_cover_maker/cli/ui/screens/render.py
spotify_cover_maker/cli/ui/sidebar.py
spotify_cover_maker/models/__init__.py
spotify_cover_maker/models/covers.py
spotify_cover_maker/models/state.py
spotify_cover_maker/rendering/__init__.py
spotify_cover_maker/rendering/plan.py
spotify_cover_maker/rendering/render.py
spotify_cover_maker/templates/gradient.svg
spotify_cover_maker-1.0.0.dist-info/LICENSE
spotify_cover_maker-1.0.0.dist-info/METADATA
spotify_cover_maker-1.0.0.dist-info/WHEEL
spotify_cover_maker-1.0.0.dist-info/entry_points.txt
spotify_cover_maker-1.0.0.dist-info/RECORD
